AnimazePy/AnimazeWrapper.py
AnimazePy/__init__.py
AnimazePy-1.0.1.dist-info/LICENSE
AnimazePy-1.0.1.dist-info/METADATA
AnimazePy-1.0.1.dist-info/WHEEL
AnimazePy-1.0.1.dist-info/top_level.txt
AnimazePy-1.0.1.dist-info/RECORD
